{
 "Maker": "John Sayre (1771–1852)",
 "Date": "ca. 1800",
 "Geography": "Mid-Atlantic, New York, New York, United States",
 "Culture": "American",
 "Medium": "Silver",
 "Dimensions": "L. 7 5/8 in. (19.4 cm)",
 "Classification": "Silver",
 "Credit Line": "Bequest of Alphonso T. Clearwater, 1933",
 "Accession Number": "33.120.600",
 "Who": [
  "Joel Sayre",
  "John Sayre"
 ],
 "What": [
  "Metal",
  "Silver",
  "Tongs"
 ],
 "Where": [
  "North and Central America",
  "United States",
  "New York",
  "New York City"
 ],
 "In the Museum": "American Decorative Arts",
 "Heilbrunn Timeline of Art History": "The United States, 1600–1800 A.D.",
 "MetPublications": "Search for related Met publications",
 "id": 10009039,
 "gallery-id": 774,
 "image": "http://images.metmuseum.org/CRDImages/ad/original/97975.jpg",
 "related-artworks": [
  10009040,
  10005663,
  10007646,
  10008303,
  10008399
 ],
 "Provenance": [
  "Alphonso T. Clearwater, Kingston, New York, until died 1933"
 ],
 "_links": {
  "self": {
   "href": "http://scrapi.org/object/10009039"
  }
 }
}