{
 "Date": "1850s",
 "Medium": "Albumen silver print",
 "Dimensions": [
  "Image 10.4 x 17.3 cm (4 1/8 x 6 13/16 in.)",
  "Mount 27.5 x 23.1 cm (10 13/16 x 9 1/8 in.)"
 ],
 "Classification": "Photographs",
 "Credit Line": "Gilman Collection, Museum Purchase, 2005",
 "Accession Number": "2005.100.948.1 (9b)",
 "Who": "Unknown",
 "What": [
  "Photographs",
  "Albumen silver prints"
 ],
 "When": "A.D. 1800-1900",
 "In the Museum": "Photographs",
 "id": 190041517,
 "related-artworks": [
  190011576,
  190011793,
  190011794,
  190012616,
  190012631
 ],
 "Provenance": [
  "(Christie's South Kensington, April 21, 1988, Lot 183)",
  "Gilman Paper Company Collection, New York"
 ],
 "_links": {
  "self": {
   "href": "http://scrapi.org/object/190041517"
  }
 }
}