{
 "Date": "1938",
 "Medium": "Gelatin silver print",
 "Dimensions": "7 1/16 x 7 3/16",
 "Classification": "Photographs",
 "Credit Line": "Gilman Collection, Purchase, Warner Communications Inc. Purchase Fund, by exchange, 2005",
 "Accession Number": "2005.100.643",
 "Rights and Reproduction": "© 2011 Artists Rights Society (ARS), New York",
 "Who": "Hans Bellmer",
 "What": [
  "Photographs",
  "Gelatin silver prints"
 ],
 "Where": [
  "Europe",
  "Germany"
 ],
 "When": "A.D. 1900-present",
 "In the Museum": "Photographs",
 "Heilbrunn Timeline of Art History": [
  "Photography and Surrealism",
  "Surrealism",
  "Central Europe (Austria, Germany, and Switzerland), 1900 A.D.–present"
 ],
 "MetPublications": "Search for related Met publications",
 "id": 190039305,
 "image": "http://images.metmuseum.org/CRDImages/ph/original/DP284322.jpg",
 "related-artworks": [
  190017173,
  190017298,
  190016971,
  190017095,
  190017174
 ],
 "Provenance": [
  "Estate of Hans Bellmer",
  "Adam J. Boxer",
  "Gilman Paper Company Collection, New York, October 9, 1997"
 ],
 "_links": {
  "self": {
   "href": "http://scrapi.org/object/190039305"
  }
 }
}