{
 "Date": "1890s–1900s",
 "Medium": "Gelatin silver print",
 "Dimensions": "13.5 x 20.6 cm. (5  5/16  x 8  1/8  in.)",
 "Classification": "Photographs",
 "Credit Line": "Gift of Shepherd Gallery Associates, in memory of John J. McKendry, 1976",
 "Accession Number": "1976.549.2",
 "Who": "José Frappa",
 "What": [
  "Photographs",
  "Gelatin silver prints"
 ],
 "Where": [
  "Europe",
  "France"
 ],
 "In the Museum": "Photographs",
 "Heilbrunn Timeline of Art History": [
  "France, 1800–1900 A.D.",
  "France, 1900 A.D.–present"
 ],
 "MetPublications": "Search for related Met publications",
 "id": 190013514,
 "related-artworks": [
  90002096,
  90002096,
  190061210,
  190061346
 ],
 "Provenance": [
  "Shepherd Gallery"
 ],
 "_links": {
  "self": {
   "href": "http://scrapi.org/object/190013514"
  }
 }
}