{
 "Date": "1800–1850",
 "Culture": "French",
 "Classification": "Daggers",
 "Credit Line": "Gift of Jean Jacques Reubell, in memory of his mother, Julia C. Coster, and of his wife, Adeline E. Post, both of New York City, 1926",
 "Accession Number": "26.145.215a, b",
 "What": [
  "Arms",
  "Edged weapons",
  "Knives",
  "Cases",
  "Sheaths",
  "Daggers",
  "Dirks"
 ],
 "Where": [
  "Europe",
  "France"
 ],
 "When": "A.D. 1800-1900",
 "In the Museum": "Arms and Armor",
 "Heilbrunn Timeline of Art History": "France, 1800–1900 A.D.",
 "MetPublications": "Search for related Met publications",
 "id": 40010919,
 "related-artworks": [
  40010920,
  40010921,
  40003416,
  40010912,
  40011044
 ],
 "_links": {
  "self": {
   "href": "http://scrapi.org/object/40010919"
  }
 }
}