{
 "Artist": "or possibly by Marcantonio Franceschini (Italian, Bologna 1648–1729 Bologna)",
 "Date": "1670–1700",
 "Medium": "Brush and brown wash, highlighted with white and cream gouache (partly oxidized), over a preliminary freehand and ruled underdrawing in charcoal, outlines stylus-incised for transfer, on four glued sheets of light tan paper with deckled borders.  Traces of framing outlines stylus-ruled along upper, right, and bottom borders",
 "Dimensions": "18-1/8 x 14-3/16 in.  (46 x 36 cm), irregular borders",
 "Classification": "Drawings",
 "Credit Line": "Rogers Fund, 1966",
 "Accession Number": "66.14",
 "Who": [
  "Marcantonio Franceschini",
  "Carlo Cignani"
 ],
 "What": [
  "Drawings",
  "Paper",
  "Watercolors",
  "Gouache",
  "Charcoal",
  "Underdrawings"
 ],
 "Where": [
  "Europe",
  "Italy"
 ],
 "When": "A.D. 1600-1800",
 "In the Museum": "Drawings and Prints",
 "MetPublications": "Search for related Met publications",
 "id": 90005870,
 "image": "http://images.metmuseum.org/CRDImages/dp/original/DP801337.jpg",
 "related-artworks": [
  90050151,
  90065353,
  90065352,
  90065354,
  90065355
 ],
 "Provenance": [
  "Sir Joshua Reynolds (British, Plympton 1723–1792 London)"
 ],
 "_links": {
  "self": {
   "href": "http://scrapi.org/object/90005870"
  }
 }
}