{
 "Publisher": "Ernst Wasmuth (Berlin)",
 "Date": "1910",
 "Medium": "Lithographic print with dark grey ink",
 "Dimensions": [
  "sheet 25 1/8 x 15 7/8 in. (63.8 x 40.3 cm)",
  "mount 22 x 28 in. (55.9 x 71.1 cm)"
 ],
 "Classification": "Prints",
 "Credit Line": "Purchase, Emily Crane Chadbourne Bequest, 1972",
 "Accession Number": "1972.607.50",
 "Who": [
  "Frank Lloyd Wright",
  "Ernst Wasmuth"
 ],
 "What": [
  "Prints",
  "Ink",
  "Planographic prints",
  "Lithographs"
 ],
 "Where": [
  "Europe",
  "Germany"
 ],
 "When": "A.D. 1900-present",
 "In the Museum": "Drawings and Prints",
 "Heilbrunn Timeline of Art History": [
  "Frank Lloyd Wright (1867–1959)",
  "The Arts and Crafts Movement in America",
  "Art Nouveau",
  "America Comes of Age 1876–1900",
  "Design, 1900–25",
  "Central Europe (Austria, Germany, and Switzerland), 1900 A.D.–present"
 ],
 "MetPublications": "Search for related Met publications",
 "id": 90055231,
 "related-artworks": [
  90054276,
  90055232,
  90055233,
  90055234,
  90055223
 ],
 "Provenance": [
  "Mr. and Mrs. Raymond V. Stevenson",
  "Francis W. Little (American, 19th–20th century)"
 ],
 "_links": {
  "self": {
   "href": "http://scrapi.org/object/90055231"
  }
 }
}