{
 "Date": "17th–18th century",
 "Culture": "French",
 "Medium": "Gilt bronze",
 "Dimensions": "3 3/4 x 3 1/8 in.  (9.5 x 7.9 cm)",
 "Classification": "Metalwork",
 "Credit Line": "Gift of J. Pierpont Morgan, 1906",
 "Accession Number": "07.225.510.46",
 "What": [
  "Metal",
  "Copper alloy",
  "Metalwork",
  "Bronze",
  "Gilt",
  "Plate",
  "Ormolu"
 ],
 "Where": [
  "Europe",
  "France"
 ],
 "When": "A.D. 1600-1800",
 "In the Museum": "European Sculpture and Decorative Arts",
 "Heilbrunn Timeline of Art History": "France, 1600–1800 A.D.",
 "MetPublications": "Search for related Met publications",
 "id": 120004341,
 "image": "http://images.metmuseum.org/CRDImages/es/original/3431.jpg",
 "related-artworks": [
  120004305,
  120004309,
  120004313,
  120004319,
  120004321
 ],
 "Provenance": [
  "Georges Hoentschel"
 ],
 "_links": {
  "self": {
   "href": "http://scrapi.org/object/120004341"
  }
 }
}