{
 "Date": "1941, printed ca. 1970",
 "Medium": "Gelatin silver print",
 "Dimensions": "16.2 x 22.4 cm. (6  3/8  x 8  13/16  in.)",
 "Classification": "Photographs",
 "Credit Line": "Gift of Arnold H. Crane, 1972",
 "Accession Number": "1972.742.20",
 "Rights and Reproduction": "© Walker Evans Archive, The Metropolitan Museum of Art",
 "Who": "Walker Evans",
 "What": [
  "Photographs",
  "Gelatin silver prints"
 ],
 "Where": [
  "North and Central America",
  "United States"
 ],
 "When": "A.D. 1900-present",
 "In the Museum": "Photographs",
 "Heilbrunn Timeline of Art History": [
  "Walker Evans (1903–1975)",
  "Kodak and the Rise of Amateur Photography",
  "Early Documentary Photography",
  "The United States and Canada, 1900 A.D.–present"
 ],
 "MetPublications": "Search for related Met publications",
 "id": 190012397,
 "image": "http://images.metmuseum.org/CRDImages/ph/original/DP102784.jpg",
 "related-artworks": [
  190011732,
  190011722,
  190011734,
  190011723,
  190011735
 ],
 "Provenance": [
  "Arnold Crane"
 ],
 "_links": {
  "self": {
   "href": "http://scrapi.org/object/190012397"
  }
 }
}